[{
   	 "owner_id": 752833,
   	 "pet_id": 90608,
   	 "chip_id": 2684931842,
   	 "first_name": "Spot",
   	 "last_name": "Aguirre",
   	 "species": "dog",
   	 "breed": "dolmation",
   	 "age": 9,
   	 "weight": 64,
   	 "sex": "M"
    },
    {
   	 "owner_id": 602281,
   	 "pet_id": 39471,
   	 "chip_id": 4286286528,
   	 "first_name": "Mr. Bing",
   	 "last_name": "James",
   	 "species": "dog",
   	 "breed": "poodle",
   	 "age": 5,
   	 "weight": 59,
   	 "sex": "M"
    },
    {
   	 "owner_id": 365542,
   	 "pet_id": 48619,
   	 "chip_id": 6522709402,
   	 "first_name": "Buddy",
   	 "last_name": "Buckley",
   	 "species": "dog",
   	 "breed": "pitbull",
   	 "age": 4,
   	 "weight": 102,
   	 "sex": "F"
    },
    {
   	 "owner_id": 781523,
   	 "pet_id": 35851,
   	 "chip_id": 4749934929,
   	 "first_name": "Socks",
   	 "last_name": "Everett",
   	 "species": "cat",
   	 "breed": "calico",
   	 "age": 20,
   	 "weight": 12,
   	 "sex": "F"
    },
    {
   	 "owner_id": 837742,
   	 "pet_id": 70671,
   	 "chip_id": 6047761976,
   	 "first_name": "Max",
   	 "last_name": "Reid",
   	 "species": "dog",
   	 "breed": "pitbull",
   	 "age": 12,
   	 "weight": 65,
   	 "sex": "M"
    },
    {
   	 "owner_id": 837742,
   	 "pet_id": 46431,
   	 "chip_id": 2547744976,
   	 "first_name": "Alfred",
   	 "last_name": "Reid",
   	 "species": "dog",
   	 "breed": "german_shephard",
   	 "age": 8,
   	 "weight": 59,
   	 "sex": "M"
    },
    {
   	 "owner_id": 566256,
   	 "pet_id": 84471,
   	 "chip_id": 3518244576,
   	 "first_name": "Kitty",
   	 "last_name": "Santiago",
   	 "species": "cat",
   	 "breed": "tabby",
   	 "age": 4,
   	 "weight": 10,
   	 "sex": "F"
    },
    {
   	 "owner_id": 866118,
   	 "pet_id": 48775,
   	 "chip_id": 6237997004,
   	 "first_name": "Daisy",
   	 "last_name": "Norton",
   	 "species": "dog",
   	 "breed": "poodle",
   	 "age": 1,
   	 "weight": 35,
   	 "sex": "F"
    },
    {
   	 "owner_id": 284564,
   	 "pet_id": 98765,
   	 "chip_id": 1706228841,
   	 "first_name": "Sandy",
   	 "last_name": "Cervantes",
   	 "species": "dog",
   	 "breed": "labrador",
   	 "age": 3,
   	 "weight": 74,
   	 "sex": "F"
    },
    {
   	 "owner_id": 817092,
   	 "pet_id": 76543,
   	 "chip_id": 6827396840,
   	 "first_name": "Lola",
   	 "last_name": "Robles",
   	 "species": "cat",
   	 "breed": "persian",
   	 "age": 15,
   	 "weight": 10,
   	 "sex": "F"
    },
    {
   	 "owner_id": 899237,
   	 "pet_id": 43543,
   	 "chip_id": 4982736840,
   	 "first_name": "Kiki",
   	 "last_name": "Lane",
   	 "species": "cat",
   	 "breed": "maine_coon",
   	 "age": 5,
   	 "weight": 15,
   	 "sex": "F"
    },
    {
   	 "owner_id": 885604,
   	 "pet_id": 90876,
   	 "chip_id": 4379960296,
   	 "first_name": "Toby",
   	 "last_name": "Bowen",
   	 "species": "dog",
   	 "breed": "daschund",
   	 "age": 7,
   	 "weight": 28,
   	 "sex": "M"
    },
    {
   	 "owner_id": 674397,
   	 "pet_id": 80765,
   	 "chip_id": 6468550619,
   	 "first_name": "Fang",
   	 "last_name": "Galloway",
   	 "species": "dog",
   	 "breed": "husky",
   	 "age": 8,
   	 "weight": 57,
   	 "sex": "M"
    },
    {
   	 "owner_id": 864123,
   	 "pet_id": 77630,
   	 "chip_id": 6493437297,
   	 "first_name": "Whiskers",
   	 "last_name": "Garcia",
   	 "species": "cat",
   	 "breed": "siamese",
   	 "age": 2,
   	 "weight": 12,
   	 "sex": "F"
    },
    {
   	 "owner_id": 588863,
   	 "pet_id": 64319,
   	 "chip_id": 5196502091,
   	 "first_name": "Fluffy",
   	 "last_name": "Salinas",
   	 "species": "cat",
   	 "breed": "sphynx",
   	 "age": 10,
   	 "weight": 8,
   	 "sex": "F"
    },
    {
   	 "owner_id": 522709,
   	 "pet_id": 56720,
   	 "chip_id": 8769946197,
   	 "first_name": "Sammy",
   	 "last_name": "Greene",
   	 "species": "dog",
   	 "breed": "pug",
   	 "age": 3,
   	 "weight": 22,
   	 "sex": "M"
    },
    {
   	 "owner_id": 284564,
   	 "pet_id": 90672,
   	 "chip_id": 6177737992,
   	 "first_name": "Chloe",
   	 "last_name": "Cervantes",
   	 "species": "dog",
   	 "breed": "poodle",
   	 "age": 6,
   	 "weight": 36,
   	 "sex": "F"
    },
    {
   	 "owner_id": 837742,
   	 "pet_id": 84763,
   	 "chip_id": 6683530499,
   	 "first_name": "Mittens",
   	 "last_name": "Reid",
   	 "species": "cat",
   	 "breed": "bengal",
   	 "age": 11,
   	 "weight": 13,
   	 "sex": "F"
    },
    {
   	 "owner_id": 522709,
   	 "pet_id": 82763,
   	 "chip_id": 8683530499,
   	 "first_name": "Maxwell",
   	 "last_name": "Greene",
   	 "species": "cat",
   	 "breed": "persian",
   	 "age": 17,
   	 "weight": 12,
   	 "sex": "M"
    }
]

